metrc/__init__.py
metrc/client.py
metrc/api/__init__.py
metrc/api/facilities.py
metrc_client_python-0.0.1.dist-info/LICENSE.txt
metrc_client_python-0.0.1.dist-info/METADATA
metrc_client_python-0.0.1.dist-info/WHEEL
metrc_client_python-0.0.1.dist-info/top_level.txt
metrc_client_python-0.0.1.dist-info/RECORD
