Metadata-Version: 2.1
Name: metrc-client-python
Version: 0.0.1
Summary: Python client library for accessing the Metrc API
Home-page: https://github.com/jessewilliamfreeman/metrc-python
Author: Jesse Freeman
Author-email: jessewilliamfreeman@gmail.com
License: UNKNOWN
Platform: UNKNOWN
Classifier: Development Status :: 3 - Alpha
Classifier: Programming Language :: Python :: 3
Requires-Python: >=3.6
License-File: LICENSE.txt
Requires-Dist: requests
